[
{
  "id" : 1,
  "img" :"../images/fdf276acdcd102cfb2bd2c996ab27efa.jpg@!200w-c",
  "name" : "缸体1226*420*925  柜体1226*42 奇溢自然 智能屏风生态鱼缸  1米2 3开柜门  白色 STR-1200P  白色",
  "price" : "￥4,291.20",
  "newprice": "￥3,576.00" 
	},
	{
  "id" : 2,
  "img" :"../images/fdf276acdcd102cfb2bd2c996ab27efa.jpg@!200w-c",
  "name" : "缸体1226*420*925  柜体1226*42 奇溢自然 智能屏风生态鱼缸  1米2 3开柜门  白色 STR-1200P  白色",
  "price" : "￥4,291.20",
  "newprice": "￥3,576.00" 
	},
	{
  "id" : 3,
  "img" :"../images/fdf276acdcd102cfb2bd2c996ab27efa.jpg@!200w-c",
  "name" : "缸体1226*420*925  柜体1226*42 奇溢自然 智能屏风生态鱼缸  1米2 3开柜门  白色 STR-1200P  白色",
  "price" : "￥4,291.20",
  "newprice": "￥3,576.00" 
	},
	{
  "id" : 4,
  "img" :"../images/7cebe37a5c848fe461f7494489ba3211.jpg@!200w-c",
  "name" : "奇溢自然 智能屏风生态鱼缸 1米2 3开柜门  红色 STR-1200P",
  "price" : "￥291.20",
  "newprice": "￥3,576.00" 
	},
{
  "id" : 5,
  "img" :"../images/7cebe37a5c848fe461f7494489ba3211.jpg@!200w-c",
  "name" : "奇溢自然 智能屏风生态鱼缸 1米2 3开柜门  红色 STR-1200P",
  "price" : "￥291.20",
  "newprice": "￥3,576.00" 
	},
	{
  "id" : 6,
  "img" :"../images/7cebe37a5c848fe461f7494489ba3211.jpg@!200w-c",
  "name" : "奇溢自然 智能屏风生态鱼缸 1米2 3开柜门  红色 STR-1200P",
  "price" : "￥291.20",
  "newprice": "￥3,576.00" 
	},
	{
  "id" : 7,
  "img" :"../images/7cebe37a5c848fe461f7494489ba3211.jpg@!200w-c",
  "name" : "奇溢自然 智能屏风生态鱼缸 1米2 3开柜门  红色 STR-1200P",
  "price" : "￥291.20",
  "newprice": "￥3,576.00" 
	},
	{
  "id" : 8,
  "img" :"../images/7cebe37a5c848fe461f7494489ba3211.jpg@!200w-c",
  "name" : "奇溢自然 智能屏风生态鱼缸 1米2 3开柜门  红色 STR-1200P",
  "price" : "￥291.20",
  "newprice": "￥3,576.00" 
	},
	{
  "id" : 9,
  "img" :"../images/7cebe37a5c848fe461f7494489ba3211.jpg@!200w-c",
  "name" : "奇溢自然 智能屏风生态鱼缸 1米2 3开柜门  红色 STR-1200P",
  "price" : "￥291.20",
  "newprice": "￥3,576.00" 
	},
	{
  "id" : 11,
  "img" :"../images/fdf276acdcd102cfb2bd2c996ab27efa.jpg@!200w-c",
  "name" : "缸体1226*420*925  柜体1226*42 奇溢自然 智能屏风生态鱼缸  1米2 3开柜门  白色 STR-1200P  白色",
  "price" : "￥4,291.20",
  "newprice": "￥3,576.00" 
	},
  {
  "id" : 12,
  "img" :"../images/fdf276acdcd102cfb2bd2c996ab27efa.jpg@!200w-c",
  "name" : "缸体1226*420*925  柜体1226*42 奇溢自然 智能屏风生态鱼缸  1米2 3开柜门  白色 STR-1200P  白色",
  "price" : "￥4,291.20",
  "newprice": "￥3,576.00" 
  },
  {
  "id" : 13,
  "img" :"../images/fdf276acdcd102cfb2bd2c996ab27efa.jpg@!200w-c",
  "name" : "缸体1226*420*925  柜体1226*42 奇溢自然 智能屏风生态鱼缸  1米2 3开柜门  白色 STR-1200P  白色",
  "price" : "￥4,291.20",
  "newprice": "￥3,576.00" 
  },
  {
  "id" : 14,
  "img" :"../images/fdf276acdcd102cfb2bd2c996ab27efa.jpg@!200w-c",
  "name" : "缸体1226*420*925  柜体1226*42 奇溢自然 智能屏风生态鱼缸  1米2 3开柜门  白色 STR-1200P  白色",
  "price" : "￥4,291.20",
  "newprice": "￥3,576.00" 
  },
  {
  "id" : 15,
  "img" :"../images/fdf276acdcd102cfb2bd2c996ab27efa.jpg@!200w-c",
  "name" : "缸体1226*420*925  柜体1226*42 奇溢自然 智能屏风生态鱼缸  1米2 3开柜门  白色 STR-1200P  白色",
  "price" : "￥4,291.20",
  "newprice": "￥3,576.00" 
  },
  {
  "id" : 16,
  "img" :"../images/fdf276acdcd102cfb2bd2c996ab27efa.jpg@!200w-c",
  "name" : "缸体1226*420*925  柜体1226*42 奇溢自然 智能屏风生态鱼缸  1米2 3开柜门  白色 STR-1200P  白色",
  "price" : "￥4,291.20",
  "newprice": "￥3,576.00" 
  },
  {
  "id" : 17,
  "img" :"../images/fdf276acdcd102cfb2bd2c996ab27efa.jpg@!200w-c",
  "name" : "缸体1226*420*925  柜体1226*42 奇溢自然 智能屏风生态鱼缸  1米2 3开柜门  白色 STR-1200P  白色",
  "price" : "￥4,291.20",
  "newprice": "￥3,576.00" 
  },
  {
  "id" : 18,
  "img" :"../images/fdf276acdcd102cfb2bd2c996ab27efa.jpg@!200w-c",
  "name" : "缸体1226*420*925  柜体1226*42 奇溢自然 智能屏风生态鱼缸  1米2 3开柜门  白色 STR-1200P  白色",
  "price" : "￥4,291.20",
  "newprice": "￥3,576.00" 
  },
	]